rcplot/__init__.py
rcplot/__main__.py
rcplot/cover_error.py
rcplot/f1.py
rcplot/utils.py
rcplot-2023.1001a0.dist-info/LICENCE
rcplot-2023.1001a0.dist-info/METADATA
rcplot-2023.1001a0.dist-info/WHEEL
rcplot-2023.1001a0.dist-info/entry_points.txt
rcplot-2023.1001a0.dist-info/top_level.txt
rcplot-2023.1001a0.dist-info/RECORD
